sha_rs-1.0.0.dist-info/METADATA
sha_rs-1.0.0.dist-info/WHEEL
sha_rs-1.0.0.dist-info/license_files/LICENSE
sha_rs/__init__.py
sha_rs/sha_rs.cpython-310-aarch64-linux-gnu.so
sha_rs-1.0.0.dist-info/RECORD
