Metadata-Version: 2.1
Name: sha_rs
Version: 1.0.0
Classifier: Programming Language :: Rust
Classifier: Programming Language :: Python :: Implementation :: CPython
Classifier: Programming Language :: Python :: Implementation :: PyPy
License-File: LICENSE
Author: Seok Won <ikr@kakao.com>
Author-email: Seok Won <ikr@kakao.com>
License: MIT
Requires-Python: >=3.7
